zech.py
zech-0.1.1.dist-info/WHEEL
zech-0.1.1.dist-info/METADATA
zech-0.1.1.dist-info/RECORD
