Metadata-Version: 2.1
Name: zech
Version: 0.1.1
Summary: Visit me at https://zech.codes
License: MIT
Author: Zech Zimmerman
Author-email: hi@zech.codes
Requires-Python: >=3.9,<4.0
Classifier: License :: OSI Approved :: MIT License
Classifier: Programming Language :: Python :: 3
Classifier: Programming Language :: Python :: 3.9
